PAMI/__init__.py
PAMI/AssociationRules/__init__.py
PAMI/AssociationRules/basic/_ARWithLeverage.py
PAMI/AssociationRules/basic/_ARWithLift.py
PAMI/AssociationRules/basic/_RuleMiner.py
PAMI/AssociationRules/basic/__init__.py
PAMI/AssociationRules/basic/abstract.py
PAMI/AssociationRules/basic/confidence.py
PAMI/AssociationRules/basic/leverage.py
PAMI/AssociationRules/basic/lift.py
PAMI/contiguousFrequentPattern/__init__.py
PAMI/contiguousFrequentPattern/basic/PositionMining.py
PAMI/contiguousFrequentPattern/basic/__init__.py
PAMI/contiguousFrequentPattern/basic/abstract.py
PAMI/correlatedPattern/__init__.py
PAMI/correlatedPattern/basic/CoMine.py
PAMI/correlatedPattern/basic/CoMinePlus.py
PAMI/correlatedPattern/basic/_CoMine.py
PAMI/correlatedPattern/basic/__init__.py
PAMI/correlatedPattern/basic/abstract.py
PAMI/coveragePattern/__init__.py
PAMI/coveragePattern/basic/CMine.py
PAMI/coveragePattern/basic/CPPG.py
PAMI/coveragePattern/basic/__init__.py
PAMI/coveragePattern/basic/abstract.py
PAMI/extras/__init__.py
PAMI/extras/convertMultiTSIntoFuzzy.py
PAMI/extras/generateLatexGraphFile.py
PAMI/extras/plotPointOnMap.py
PAMI/extras/plotPointOnMap_dump.py
PAMI/extras/scatterPlotSpatialPoints.py
PAMI/extras/topKPatterns.py
PAMI/extras/uncertaindb_convert.py
PAMI/extras/calculateMISValues/__init__.py
PAMI/extras/calculateMISValues/usingBeta.py
PAMI/extras/calculateMISValues/usingSD.py
PAMI/extras/convert/CSV2BitInteger.py
PAMI/extras/convert/CSV2Integer.py
PAMI/extras/convert/CSV2Parquet.py
PAMI/extras/convert/DF2DB.py
PAMI/extras/convert/Parquet2CSV.py
PAMI/extras/convert/Subgraphs2FlatTransactions.py
PAMI/extras/convert/_CSV2Parquet.py
PAMI/extras/convert/_DF2DB.py
PAMI/extras/convert/__init__.py
PAMI/extras/convert/_denseDF2DB.py
PAMI/extras/convert/_sparseDF2DB.py
PAMI/extras/convert/denseDF2DB.py
PAMI/extras/convert/fasta_to_csv.py
PAMI/extras/convert/sparseDF2DB.py
PAMI/extras/convert/_DF2DB/DF2DBPlus.py
PAMI/extras/convert/_DF2DB/TransactionDB2denseDF.py
pami-2026.1.19.1.dist-info/LICENSE
pami-2026.1.19.1.dist-info/METADATA
pami-2026.1.19.1.dist-info/WHEEL
pami-2026.1.19.1.dist-info/top_level.txt
pami-2026.1.19.1.dist-info/RECORD
