Metadata-Version: 2.1
Name: pami
Version: 2026.1.19.1
Summary: This software is being developed at the University of Aizu, Aizu-Wakamatsu, Fukushima, Japan
Home-page: https://github.com/udayLab/PAMI
Author: Rage Uday Kiran
Author-email: uday.rage@gmail.com
License: GPLv3
Platform: UNKNOWN
Classifier: Development Status :: 5 - Production/Stable
Classifier: Programming Language :: Python :: 3
Classifier: License :: OSI Approved :: GNU General Public License v3 (GPLv3)
Classifier: Operating System :: OS Independent
Requires-Python: >=3.5
License-File: LICENSE
Requires-Dist: psutil
Requires-Dist: pandas
Requires-Dist: plotly
Requires-Dist: matplotlib
Requires-Dist: resource
Requires-Dist: validators
Requires-Dist: urllib3
Requires-Dist: Pillow
Requires-Dist: numpy
Requires-Dist: sphinx
Requires-Dist: sphinx-rtd-theme
Requires-Dist: discord.py
Requires-Dist: networkx
Requires-Dist: deprecated
Requires-Dist: fastparquet
Provides-Extra: all
Requires-Dist: cupy ; extra == 'all'
Requires-Dist: pycuda ; extra == 'all'
Requires-Dist: pyspark ; extra == 'all'
Requires-Dist: twine ; extra == 'all'
Requires-Dist: setuptools ; extra == 'all'
Requires-Dist: build ; extra == 'all'
Provides-Extra: dev
Requires-Dist: twine ; extra == 'dev'
Requires-Dist: setuptools ; extra == 'dev'
Requires-Dist: build ; extra == 'dev'
Provides-Extra: gpu
Requires-Dist: cupy ; extra == 'gpu'
Requires-Dist: pycuda ; extra == 'gpu'
Provides-Extra: spark
Requires-Dist: pyspark ; extra == 'spark'
